df_cereal/__init__.py
df_cereal/_frontend.py
df_cereal/_version.py
df_cereal/arrow_utils.py
df_cereal/arrow_widgets.py
df_cereal/channeldata.json
df_cereal/df_widget.py
df_cereal/widget_utils.py
df_cereal/labextension/package.json
df_cereal/labextension/static/399.3628af2615b682daac60.js
df_cereal/labextension/static/480.f32958e07b1906177d7b.js
df_cereal/labextension/static/486.e929ed9e4ac421f51fe3.js
df_cereal/labextension/static/486.e929ed9e4ac421f51fe3.js.LICENSE.txt
df_cereal/labextension/static/568.fcd72dc747573c03dc2d.js
df_cereal/labextension/static/745.fcc0c0d39a2648355b8e.js
df_cereal/labextension/static/745.fcc0c0d39a2648355b8e.js.LICENSE.txt
df_cereal/labextension/static/965.648b0b23b73a07fc332f.js
df_cereal/labextension/static/remoteEntry.1b9971ddec2396bb8d01.js
df_cereal/labextension/static/style.js
df_cereal/labextension/static/third-party-licenses.json
df_cereal/nbextension/index.js
df_cereal/nbextension/index.js.LICENSE.txt
df_cereal/noarch/current_repodata.json
df_cereal/noarch/current_repodata.json.bz2
df_cereal/noarch/index.html
df_cereal/noarch/repodata.json
df_cereal/noarch/repodata.json.bz2
df_cereal/noarch/repodata_from_packages.json
df_cereal/noarch/repodata_from_packages.json.bz2
df_cereal-0.0.1.data/data/share/jupyter/labextensions/df_cereal/package.json
df_cereal-0.0.1.data/data/share/jupyter/labextensions/df_cereal/static/399.3628af2615b682daac60.js
df_cereal-0.0.1.data/data/share/jupyter/labextensions/df_cereal/static/480.f32958e07b1906177d7b.js
df_cereal-0.0.1.data/data/share/jupyter/labextensions/df_cereal/static/486.e929ed9e4ac421f51fe3.js
df_cereal-0.0.1.data/data/share/jupyter/labextensions/df_cereal/static/486.e929ed9e4ac421f51fe3.js.LICENSE.txt
df_cereal-0.0.1.data/data/share/jupyter/labextensions/df_cereal/static/568.fcd72dc747573c03dc2d.js
df_cereal-0.0.1.data/data/share/jupyter/labextensions/df_cereal/static/745.fcc0c0d39a2648355b8e.js
df_cereal-0.0.1.dist-info/METADATA
df_cereal-0.0.1.dist-info/WHEEL
df_cereal-0.0.1.dist-info/licenses/LICENSE.txt
df_cereal-0.0.1.dist-info/RECORD
