Metadata-Version: 2.3
Name: df_cereal
Version: 0.0.1
Summary: df_cereal - playing with dataframe serialization
Project-URL: Homepage, https://github.com/paddymul/df_cereal
Author: Paddy Mullen
License: Copyright (c) 2019 Bloomberg
License-File: LICENSE.txt
Keywords: IPython,Jupyter,Widgets,pandas
Classifier: Framework :: Jupyter
Classifier: Intended Audience :: Developers
Classifier: Intended Audience :: Science/Research
Classifier: License :: OSI Approved :: BSD License
Classifier: Programming Language :: Python
Classifier: Programming Language :: Python :: 3
Classifier: Programming Language :: Python :: 3 :: Only
Classifier: Programming Language :: Python :: 3.7
Classifier: Programming Language :: Python :: 3.8
Classifier: Programming Language :: Python :: 3.9
Classifier: Programming Language :: Python :: 3.10
Requires-Python: >=3.8
Requires-Dist: graphlib-backport>=1.0.0
Requires-Dist: ipywidgets<9,>=7.6.0
Provides-Extra: build
Requires-Dist: build; extra == 'build'
Requires-Dist: twine; extra == 'build'
Provides-Extra: docs
Requires-Dist: graphviz>=0.20.1; extra == 'docs'
Requires-Dist: sphinx>=1.5; extra == 'docs'
Provides-Extra: jupyterlab
Requires-Dist: jupyterlab>=3.6.0; extra == 'jupyterlab'
Provides-Extra: notebook
Requires-Dist: notebook>=7.0.0; extra == 'notebook'
Provides-Extra: polars
Requires-Dist: polars>=0.20.7; extra == 'polars'
Provides-Extra: test
Requires-Dist: hypothesis>=6.88.1; extra == 'test'
Requires-Dist: nbval>=0.9; extra == 'test'
Requires-Dist: pandas>=1.3.5; extra == 'test'
Requires-Dist: polars>=0.19.4; extra == 'test'
Requires-Dist: pyarrow; extra == 'test'
Requires-Dist: pydantic>=2.5.2; extra == 'test'
Requires-Dist: pytest-cov>=3; extra == 'test'
Requires-Dist: pytest>=6; extra == 'test'
